nc_utils/__init__.py
nc_utils-0.0.0.dist-info/DESCRIPTION.rst
nc_utils-0.0.0.dist-info/METADATA
nc_utils-0.0.0.dist-info/RECORD
nc_utils-0.0.0.dist-info/WHEEL
nc_utils-0.0.0.dist-info/metadata.json
nc_utils-0.0.0.dist-info/top_level.txt
