Metadata-Version: 2.0
Name: nc-utils
Version: 0.0.0
Summary: NetCDF utils
Home-page: https://github.com/claydodo/nc_utils
Author: claydodo and his little friends (xiao huo ban)
Author-email: claydodo@foxmail.com
License: UNKNOWN
Platform: UNKNOWN
Classifier: Programming Language :: Python :: 2.7 
Classifier: Operating System :: OS Independent
